ntcore/__about__.py
ntcore/__init__.py
ntcore/client.py
ntcore/cli/__init__.py
ntcore/cli/workflow.py
ntcore/exceptions/__init__.py
ntcore/exceptions/exceptions.py
ntcore/integrations/__init__.py
ntcore/integrations/utils.py
ntcore/integrations/sklearn/__init__.py
ntcore/integrations/sklearn/utils.py
ntcore/integrations/tensorflow/__init__.py
ntcore/integrations/torch/__init__.py
ntcore/libs/__init__.py
ntcore/libs/model_serializer.py
ntcore/models/__init__.py
ntcore/models/experiment.py
ntcore/models/framework.py
ntcore/monitor/__init__.py
ntcore/monitor/monitor.py
ntcore/monitor/service_metrics.py
ntcore/monitor/system_metrics.py
ntcore/resources/__init__.py
ntcore/resources/api_async_client.py
ntcore/resources/api_client.py
ntcore/resources/encryption.py
tests/__init__.py
tests/test_monitor.py
ntcore-0.1.7.dist-info/METADATA
ntcore-0.1.7.dist-info/WHEEL
ntcore-0.1.7.dist-info/entry_points.txt
ntcore-0.1.7.dist-info/top_level.txt
ntcore-0.1.7.dist-info/RECORD
