Metadata-Version: 2.1
Name: ntcore
Version: 0.1.7
Summary: Python client for interfacing with NTCore
Home-page: https://www.nantu.io/
Maintainer: NTCore
Maintainer-email: info@nantutech.com
License: Apache 2.0
Platform: UNKNOWN
Requires-Python: >=2.7, !=3.0.*, !=3.1.*, !=3.2.*, !=3.3.*, !=3.4.*
